{
  "_comment": "Server Pilot configuration. Supports single-server and multi-server modes.",
  "_single_server": "For one server, use these top-level fields:",
  "host": "your-server.com",
  "port": 22,
  "username": "root",
  "password": "your-password",
  "key_file": "",
  "_multi_server": "For multiple servers, use the 'servers' key below (remove top-level host/port/username/password):",
  "servers": {
    "gpu-server": {
      "host": "gpu-server.example.com",
      "port": 22,
      "username": "root",
      "key_file": "~/.ssh/id_rsa",
      "_note": "SSH key auth (recommended)"
    },
    "train-box": {
      "host": "train.example.com",
      "port": 26628,
      "username": "root",
      "password": "your-password",
      "_note": "Password auth"
    }
  }
}